instacerty/__init__.py
instacerty/instacerty.py
instacerty/utils.py
instacerty/static/images/badge.png
instacerty/static/images/bg.jpg
instacerty/static/images/signature.png
intacerty-0.1.dist-info/METADATA
intacerty-0.1.dist-info/WHEEL
intacerty-0.1.dist-info/top_level.txt
intacerty-0.1.dist-info/RECORD
